mustafakilic/__init__.py
mustafakilic/channel.py
mustafakilic-0.0.1.dist-info/licenses/LICENSE
mustafakilic-0.0.1.dist-info/METADATA
mustafakilic-0.0.1.dist-info/WHEEL
mustafakilic-0.0.1.dist-info/top_level.txt
mustafakilic-0.0.1.dist-info/RECORD
