Metadata-Version: 2.4
Name: mustafakilic
Version: 0.0.1
Summary: A small example package.
Author-email: Mustafa Kılıç <klcm51@gmail.com>
Project-URL: Homepage, https://github.com/kilic-mustafa/mustafakilic
Keywords: mustafa,kilic
Classifier: Development Status :: 3 - Alpha
Classifier: Intended Audience :: Developers
Classifier: License :: OSI Approved :: MIT License
Classifier: Programming Language :: Python :: 3
Classifier: Operating System :: OS Independent
Requires-Python: >=3.10
License-File: LICENSE
Dynamic: license-file
